MANIFEST.in
README.md
setup.py
django_fuelsdk/__init__.py
django_fuelsdk/client.py
django_fuelsdk/constants.py
django_fuelsdk/fuel.py
django_fuelsdk/models.py
django_fuelsdk/tests.py
django_fuelsdk.egg-info/PKG-INFO
django_fuelsdk.egg-info/SOURCES.txt
django_fuelsdk.egg-info/dependency_links.txt
django_fuelsdk.egg-info/requires.txt
django_fuelsdk.egg-info/top_level.txt