Metadata-Version: 1.1
Name: django-fuelsdk
Version: 0.2
Summary: Django wrapper for the ExactTarget FuelSDK.
Home-page: https://github.com/roverdotcom/django-fuelsdk
Author: Johannas Heller
Author-email: johann@rover.com
License: MIT
Keywords: fuelsdk,email,django
Platform: UNKNOWN
Classifier: Environment :: Other Environment
Classifier: Environment :: Web Environment
Classifier: Intended Audience :: Developers
Classifier: License :: OSI Approved :: MIT License
Classifier: Operating System :: OS Independent
Classifier: Programming Language :: Python
Classifier: Topic :: Communications :: Email
